aiokef/__init__.py
aiokef/_static_version.py
aiokef/_version.py
aiokef/aiokef.py
aiokef-0.2.17.dist-info/LICENSE
aiokef-0.2.17.dist-info/METADATA
aiokef-0.2.17.dist-info/WHEEL
aiokef-0.2.17.dist-info/top_level.txt
aiokef-0.2.17.dist-info/RECORD
