Metadata-Version: 2.1
Name: aiokef
Version: 0.2.17
Summary: Asyncio Python API for KEF speakers.
Home-page: https://github.com/basnijholt/aiokef
Maintainer: Bas Nijholt
Maintainer-email: bas@nijho.lt
License: MIT
Download-URL: https://pypi.python.org/pypi/aiokef
Keywords: iot
Platform: UNKNOWN
Classifier: License :: OSI Approved :: MIT License
Classifier: Development Status :: 4 - Beta
Classifier: Operating System :: OS Independent
Classifier: Programming Language :: Python :: 3.7
Classifier: Programming Language :: Python :: 3.8
Classifier: Topic :: Home Automation
Requires-Python: >=3.7
Requires-Dist: async-timeout
Requires-Dist: tenacity
Provides-Extra: dev
Requires-Dist: pre-commit ; extra == 'dev'
Provides-Extra: docs
Requires-Dist: sphinx ; extra == 'docs'
Requires-Dist: sphinx-rtd-theme ; extra == 'docs'
Requires-Dist: m2r2 ; extra == 'docs'
Requires-Dist: sphinxcontrib.apidoc ; extra == 'docs'
Provides-Extra: test
Requires-Dist: pytest ; extra == 'test'
Requires-Dist: pytest-cov ; extra == 'test'
Requires-Dist: pytest-mypy ; extra == 'test'
Requires-Dist: tox ; extra == 'test'
